s3_upload_split/__init__.py
s3_upload_split-0.1.6.dist-info/WHEEL
s3_upload_split-0.1.6.dist-info/METADATA
s3_upload_split-0.1.6.dist-info/RECORD
