Metadata-Version: 2.1
Name: s3-upload-split
Version: 0.1.6
Summary: Streams the content of an iterator to multiple S3 objects based on a regular expression
Home-page: https://github.com/cscetbon/s3-upload-split
Author: Cyril Scetbon
Author-email: cscetbon@gmail.com
Requires-Python: >=3.7,<4.0
Classifier: Programming Language :: Python :: 3
Classifier: Programming Language :: Python :: 3.10
Classifier: Programming Language :: Python :: 3.7
Classifier: Programming Language :: Python :: 3.8
Classifier: Programming Language :: Python :: 3.9
Requires-Dist: anypubsub (>=0.6,<0.7)
Requires-Dist: boto3 (>=1.15.18,<2.0.0)
